metrics/__init__.py
metrics/metrics.py
models/__init__.py
models/dl.py
predictions/__init__.py
predictions/predict.py
preprocessing/__init__.py
preprocessing/preprocess.py
train/__init__.py
train/trainer.py
tokyo_jpx-0.0.39.dist-info/LICENSE
tokyo_jpx-0.0.39.dist-info/METADATA
tokyo_jpx-0.0.39.dist-info/WHEEL
tokyo_jpx-0.0.39.dist-info/top_level.txt
tokyo_jpx-0.0.39.dist-info/RECORD
