Metadata-Version: 2.1
Name: tokyo-jpx
Version: 0.0.39
Summary: Package for doing stock return predictions for the JPX Tokyo Exchange Kaggle competition.
Home-page: https://github.com/gilberto-BE/tokyo_jpx
Author: Gilberto Batres-Estrada
Author-email: Gilberto Batres-Estrada <g.batres.estrada@gmail.com>
License: MIT License        
Project-URL: Homepage, https://github.com/pypa/tokyo_jpx
Project-URL: Bug Tracker, https://github.com/pypa/tokyo_jpx/issues
Classifier: Programming Language :: Python :: 3
Classifier: License :: OSI Approved :: MIT License
Classifier: Operating System :: OS Independent
Requires-Python: >=3.7
License-File: LICENSE
